qsarmodelingpy_gui/Constants.py
qsarmodelingpy_gui/FilterHandler.py
qsarmodelingpy_gui/GAHandler.py
qsarmodelingpy_gui/HandlerFinder.py
qsarmodelingpy_gui/Interfaces.py
qsarmodelingpy_gui/MainHandler.py
qsarmodelingpy_gui/OPSHandler.py
qsarmodelingpy_gui/Plots.py
qsarmodelingpy_gui/ResultsHandler.py
qsarmodelingpy_gui/Utils.py
qsarmodelingpy_gui/ValidationHandler.py
qsarmodelingpy_gui/__init__.py
qsarmodelingpy_gui/__main__.py
qsarmodelingpy_gui/logger.py
qsarmodelingpy_gui/main.py
qsarmodelingpy_gui/runCalculations.py
qsarmodelingpy_gui/Views/about.glade
qsarmodelingpy_gui/Views/autocorrcut.glade
qsarmodelingpy_gui/Views/corrcut.glade
qsarmodelingpy_gui/Views/cross_validation.glade
qsarmodelingpy_gui/Views/external_validation.glade
qsarmodelingpy_gui/Views/ga.glade
qsarmodelingpy_gui/Views/main.glade
qsarmodelingpy_gui/Views/ops.glade
qsarmodelingpy_gui/Views/results.glade
qsarmodelingpy_gui/Views/varcut.glade
qsarmodelingpy_gui/Views/yrlno.glade
qsarmodelingpy_gui-0.2.5.dist-info/LICENSE
qsarmodelingpy_gui-0.2.5.dist-info/METADATA
qsarmodelingpy_gui-0.2.5.dist-info/WHEEL
qsarmodelingpy_gui-0.2.5.dist-info/entry_points.txt
qsarmodelingpy_gui-0.2.5.dist-info/top_level.txt
qsarmodelingpy_gui-0.2.5.dist-info/RECORD
