Metadata-Version: 2.1
Name: qsarmodelingpy-gui
Version: 0.2.5
Summary: A software for building and validating QSAR models
Home-page: https://github.com/hellmrf/QSARModelingPyInterfaces
Author: Reis Filho, H. M.; Martins, J. P. A
Author-email: helitonmrf@ufmg.br,jpam@qui.ufmg.br
License: UNKNOWN
Platform: UNKNOWN
Classifier: Programming Language :: Python :: 3
Classifier: Operating System :: OS Independent
Requires-Python: >=3.6
License-File: LICENSE
Requires-Dist: qsarmodelingpy (>=0.3.0)
Requires-Dist: pygobject (==3.30.5)
Requires-Dist: typing-extensions
Requires-Dist: coloredlogs
Requires-Dist: matplotlib
Requires-Dist: tornado
Requires-Dist: PyQt5
